skyant/data/__init__.py
skyant/data/dataset/__init__.py
skyant/data/entity/__init__.py
skyant/data/entity/config/__init__.py
skyant/data/entity/config/_common.py
skyant/data/entity/fields/__init__.py
skyant/data/entity/fields/_firestore.py
skyant/data/entity/google/__init__.py
skyant/data/entity/google/_firestore.py
skyant/data/entity/google/_pubsub.py
skyant/data/entity/google/_storage.py
skyant/data/entity/google/_tasks.py
skyant/data/entity/grpc/__init__.py
skyant/data/entity/grpc/grpc.py
skyant/data/entity/local/__init__.py
skyant/data/entity/local/_files.py
skyant/data/entity/rest/__init__.py
skyant/data/entity/rest/_general.py
skyant/data/tools/__init__.py
skyant/data/tools/e.py
skyant/data/tools/file.py
skyant/data/tools/json.py
skyant/data/tools/w.py
skyant_data-0.0.2.dist-info/LICENSE
skyant_data-0.0.2.dist-info/METADATA
skyant_data-0.0.2.dist-info/WHEEL
skyant_data-0.0.2.dist-info/top_level.txt
skyant_data-0.0.2.dist-info/RECORD
