Metadata-Version: 2.1
Name: skyant-data
Version: 0.0.2
Summary: Extended well-known objects for interaction with cloud
Home-page: https://skyant.dev
Author: Iurii Tarasenko
Author-email: info@skyant.dev
License: MIT
Project-URL: Source & issues, https://gitlab.com/skyant/python/data
Project-URL: Documentation, https://docs.skyant.dev/projects/data
Keywords: pydantic,api,rest,GCP
Classifier: Programming Language :: Python :: 3.10
Classifier: Intended Audience :: Developers
Classifier: Intended Audience :: Information Technology
Classifier: Topic :: Software Development :: Libraries :: Python Modules
Requires-Python: >=3.10
License-File: LICENSE
Requires-Dist: pydantic
Requires-Dist: PyYaml
Requires-Dist: requests
Requires-Dist: jsonschema
Requires-Dist: google-auth
Requires-Dist: google-cloud-storage
Requires-Dist: google-cloud-firestore
Requires-Dist: google-cloud-tasks
Requires-Dist: google-cloud-pubsub
